imagedominantcolor/__init__.py
imagedominantcolor/__version__.py
imagedominantcolor/dominantcolor.py
imagedominantcolor-1.0.1.dist-info/LICENSE
imagedominantcolor-1.0.1.dist-info/METADATA
imagedominantcolor-1.0.1.dist-info/WHEEL
imagedominantcolor-1.0.1.dist-info/top_level.txt
imagedominantcolor-1.0.1.dist-info/RECORD
